[
  {
    "company_name": "牧原食品股份有限公司",
    "industry": "食品加工",
    "contact_person": "",
    "phone": "",
    "email": "",
    "address": "",
    "source": "搜狗-食品厂",
    "website": "https://www.sogou.com/link?url=DSOYnZeCC_olQk1gWOKNe072uBPR5Oko06jqesMEqQY.",
    "business_scope": "牧原 食品 股份有限公司 牧原 食品 股份有限公司始创于1992年,2014年上市。现已形成集饲料加工、生猪育种、生猪养殖、屠宰加工为一体的猪肉产业链。 http://www.muyuanfoods.co... 2026-03-20 推荐您",
    "status": "未联系",
    "notes": "搜索词: 食品厂; 匹配依据: 食品; 匹配分: 3",
    "created_at": "2026-03-29 11:26"
  },
  {
    "company_name": "食品工厂公司",
    "industry": "食品加工",
    "contact_person": "",
    "phone": "",
    "email": "",
    "address": "江苏 苏... 顺企网 https://b2b.11467.com/s... 2026-03-11 推荐您搜索",
    "source": "搜狗-食品厂",
    "website": "https://www.sogou.com/link?url=hedJjaC291PuQiRPsXidblUWGsygCOZ2q4LTK2VZRG4jEyqo_EhqzynffMPiIdzIvB94c2-iahU.",
    "business_scope": "「 食品 工厂」 食品 工厂公司黄页 - 顺企网 食品厂 房洁净室装... 地址： 松江区沈砖公路5666号B栋18F 成立时间：2020-04-15 主营产品： 酒店； 西餐； 饼房； 蛋糕； 饼房用品； 工厂； 学校； 原材料 地址： ",
    "status": "未联系",
    "notes": "搜索词: 食品厂; 匹配依据: 食品厂, 食品, 地址; 匹配分: 5",
    "created_at": "2026-03-29 11:26"
  },
  {
    "company_name": "温州)有限公司",
    "industry": "食品加工",
    "contact_person": "",
    "phone": "18205871865",
    "email": "",
    "address": "",
    "source": "搜狗-食品厂 联系方式",
    "website": "https://www.sogou.com/id=91987237-b126-44af-8005-76c53e2b3e7c/keyword=%E9%A3%9F%E5%93%81%E5%8E%82%20%E8%81%94%E7%B3%BB%E6%96%B9%E5%BC%8F/sec=XCIO-E9tzAyGn6gUuUdxEA../entryTime=1774754774419/vr=11002601/tc?rcer=VGH7jSo5&&title=%E9%97%AF%E9%91%AB%E9%A3%9F%E5%93%81(%E6%B8%A9%E5%B7%9E)%E6%9C%89%E9%99%90%E5%85%AC%E5%8F%B8&dp=1&is_per=0&pno=1&clk=11&url=https%3A%2F%2Fmp.weixin.qq.com%2Fs%3Fsrc%3D11%26timestamp%3D1774754775%26ver%3D6627%26signature%3DYyDNGYtSK4oFo7b*vXNaYbFvdYbOAAG16D3gxvOfr7pDRg0gzTdP7JMaVP-IfAe18Sk2fknyhK-*T4dK8oUCCPAm0aHDRf-y-65afX2iXD74A194JCye9YxecrcWgEyL%26new%3D1%26qbExtraParams%3Dquery%253D%2525E9%2525A3%25259F%2525E5%252593%252581%2525E5%25258E%252582%252520%2525E8%252581%252594%2525E7%2525B3%2525BB%2525E6%252596%2525B9%2525E5%2525BC%25258F%2526source%253D11002601%2526docId%253Dab735a258a90e8e1-6bee54fcbd896b2a-f04b2e03416089545e10be45e8f7bdc4&vrid=11002601&wml=1&linkid=title",
    "business_scope": "闯鑫 食品 (温州)有限公司 联系方式 官方电话及传真:0577-63661958销售热线:18205871865销售热线:13806617470 微信公众号·微信公众平台 2021-07-26",
    "status": "未联系",
    "notes": "搜索词: 食品厂 联系方式; 匹配依据: 食品, 电话; 匹配分: 3",
    "created_at": "2026-03-29 11:26"
  },
  {
    "company_name": "济南大城小爱食品有限公司",
    "industry": "食品加工",
    "contact_person": "",
    "phone": "15866670555",
    "email": "",
    "address": "",
    "source": "搜狗-零食生产 联系方式",
    "website": "http://mp.weixin.qq.com/s?src=11&timestamp=1774754790&ver=6627&signature=YBnLet-m*uA--ixntPjb3Zfr3Cjhtm7sWK1fzH8X0z2dinrFJ-qRrPl25kabSE7w-KCmBwcbekTApw*b-fPjQ7pwWgBMB*uqVL7qb4uA9dA0Bhi2e484aeZ4NsFsEcCb&new=1",
    "business_scope": "食品快销圈免费推广第533期(18家展商内含 联系方式 ) 01食品快销圈推荐【公司名称】济南大城小爱食品有限公司【公司品牌】知心话【公司主营】休闲 零食 橡皮糖 联系方式 满总15866670555广告勿扰!02食品快销圈推荐【公司名称】",
    "status": "未联系",
    "notes": "搜索词: 零食生产 联系方式; 匹配依据: 零食, 电话; 匹配分: 3",
    "created_at": "2026-03-29 11:26"
  },
  {
    "company_name": "长沙很忙零食食品有限公司",
    "industry": "食品加工",
    "contact_person": "",
    "phone": "",
    "email": "",
    "address": "",
    "source": "搜狗-零食生产 联系方式",
    "website": "https://www.sogou.com/link?url=hedJjaC291OOU1q7FfpLot2XACA0BICUa1_GK1aLypm2wKelUak-kA..",
    "business_scope": "零食 糕点加盟电话、 联系方式 -安心加盟网 安心加盟网提供 零食 糕点加盟品牌总部真实详细 联系方式 。公司名称：长沙很忙 零食 食品有限公司，加盟联系电话：400-9998-082，（免费热线）可直接拨打，加盟网址等详细... 安心加盟",
    "status": "未联系",
    "notes": "搜索词: 零食生产 联系方式; 匹配依据: 零食; 匹配分: 3",
    "created_at": "2026-03-29 11:26"
  },
  {
    "company_name": "还在问12零食生产流程52人在问零食厂",
    "industry": "食品加工",
    "contact_person": "",
    "phone": "",
    "email": "",
    "address": "联系方式 52 人在问 零食生意太难做了 51 人在问",
    "source": "搜狗-零食生产 联系方式",
    "website": "https://www.sogou.com/web?query=%E9%9B%B6%E9%A3%9F%E7%94%9F%E4%BA%A7%E6%B5%81%E7%A8%8B&s_from=pc_wendaka",
    "business_scope": "「问过的人」还在问 1 2 零食生产流程 52 人在问 零食厂家联系方式 52 人在问 零食多门店地址联系方式 52 人在问 零食生意太难做了 51 人在问",
    "status": "未联系",
    "notes": "搜索词: 零食生产 联系方式; 匹配依据: 零食生产, 零食, 地址; 匹配分: 6",
    "created_at": "2026-03-29 11:26"
  },
  {
    "company_name": "武汉坚果零食厂",
    "industry": "食品加工",
    "contact_person": "",
    "phone": "15527826558",
    "email": "",
    "address": "_联系电话-武汉艾米零食品有限公司 e.51sole.com 3 . 玩具零食生产厂家-玩具零食厂家",
    "source": "搜狗-零食生产 电话",
    "website": "https://www.douyin.com/note/7203314551507455270",
    "business_scope": "QBot 正在分析问题 1 . 自己工厂生产的各种宠物零食，冻干品类齐全，联系电话18632 抖音 2 . 武汉坚果零食厂家联系地址_联系电话-武汉艾米零食品有限公司 e.51sole.com 3 . 玩具零食生产厂家-玩具零食厂家电话-食",
    "status": "未联系",
    "notes": "搜索词: 零食生产 电话; 匹配依据: 零食生产, 零食, 地址; 匹配分: 5",
    "created_at": "2026-03-29 11:26"
  },
  {
    "company_name": "还在搜加盟好想来零食加盟电话零食鸭加盟电话零食很忙官方电话零食舱总部电话零食很忙公司",
    "industry": "食品加工",
    "contact_person": "",
    "phone": "",
    "email": "",
    "address": "电话 零食很忙公司加盟",
    "source": "搜狗-零食生产 电话",
    "website": "https://www.sogou.com?user_ip=183&bh=1&hintidx=0&query=%E5%8A%A0%E7%9B%9F%E5%A5%BD%E6%83%B3%E6%9D%A5%E9%9B%B6%E9%A3%9F%E5%8A%A0%E7%9B%9F%E7%94%B5%E8%AF%9D&w=01020600&sessiontime=1774754795307&interation=&interV=kKIOkrELjbkRmLkElbkTkKIMkrELjboImLkEk74TkKIRmLkEk78TkKILkY==_-115092183&htdbg=on&ie=utf8&s_from=hint_middle",
    "business_scope": "大家还在搜 加盟好想来零食加盟电话 零食鸭加盟电话 零食很忙官方电话 零食舱总部电话 零食很忙公司地址电话 零食很忙公司加盟电话 零食很忙总部地址电话 零食很忙采购部电话 零食很忙客服电话 零食很忙加盟咨询电话",
    "status": "未联系",
    "notes": "搜索词: 零食生产 电话; 匹配依据: 零食, 地址; 匹配分: 4",
    "created_at": "2026-03-29 11:26"
  },
  {
    "company_name": "北京市绿得食品有限责任公司",
    "industry": "食品加工",
    "contact_person": "",
    "phone": "0106***0613",
    "email": "laobut***@163.com",
    "address": "",
    "source": "搜狗-零食生产 电话",
    "website": "https://www.sogou.com/link?url=hedJjaC291PVK4K_Q5dwJ9xxLxpftxcWDvVEimVLytFWEFB2NS1BidM7Xe6uZ5eq",
    "business_scope": "北京市绿得食品有限责任公司 电话 号码 北京市绿得食品有限责任公司 客服电话: 0106***0613 查看完整号码 客服电话: 0108***5383 传真: 0106***4553 邮箱: laobut***@163.com 销售电话:",
    "status": "未联系",
    "notes": "搜索词: 零食生产 电话; 匹配依据: 电话, 邮箱; 匹配分: 3",
    "created_at": "2026-03-29 11:26"
  },
  {
    "company_name": "南京糖糖屋零食物语食品有限公司",
    "industry": "食品加工",
    "contact_person": "",
    "phone": "0258***3196",
    "email": "li***@tangtangwu.com",
    "address": "",
    "source": "搜狗-零食生产 电话",
    "website": "https://www.sogou.com/link?url=hedJjaC291PVK4K_Q5dwJ9xxLxpftxcWPDM7LLR7_jriXXnf-FQ5Kzh3ZfoXRJBg",
    "business_scope": "南京糖糖屋 零食 物语食品有限公司 电话 号码 南京糖糖屋 零食 物语食品有限公司 电话 ： 0258***3196 查看完整号码 电话 ： 0258***9446 邮箱： li***@tangtangwu.com 地址： 江苏省 南京市 ",
    "status": "未联系",
    "notes": "搜索词: 零食生产 电话; 匹配依据: 零食, 电话, 邮箱; 匹配分: 5",
    "created_at": "2026-03-29 11:26"
  }
]